kitti3/__init__.py
kitti3/_pkg_info.py
kitti3/main.py
kitti3-0.4.1.dist-info/LICENSE
kitti3-0.4.1.dist-info/METADATA
kitti3-0.4.1.dist-info/WHEEL
kitti3-0.4.1.dist-info/entry_points.txt
kitti3-0.4.1.dist-info/top_level.txt
kitti3-0.4.1.dist-info/RECORD
