Metadata-Version: 2.1
Name: kitti3
Version: 0.4.1
Summary: Kitti3 - Kitty drop down terminal service for i3wm
Home-page: https://github.com/LandingEllipse/kitti3
Author: Ariel Ladegaard
Author-email: arl13@aber.ac.uk
License: BSD 3-Clause
Keywords: drop down terminal kitty i3 i3wm quake guake
Platform: UNKNOWN
Classifier: Development Status :: 4 - Beta
Classifier: Environment :: Console
Classifier: Intended Audience :: End Users/Desktop
Classifier: License :: OSI Approved :: BSD License
Classifier: Natural Language :: English
Classifier: Operating System :: POSIX :: Linux
Classifier: Environment :: X11 Applications
Classifier: Programming Language :: Python :: 3 :: Only
Classifier: Topic :: Terminals :: Terminal Emulators/X Terminals
Classifier: Topic :: Desktop Environment :: Window Managers
Requires-Python: >=3.6
Requires-Dist: i3ipc (>=2.0.0)
